{
    "address": "Penwith Road, London SW18",
    "price": "\u00a3550,000",
    "beds": "2 beds",
    "area": null,
    "sqm": 59.1,
    "sqft": 636.0,
    "text": "Penwith Road, London, SW18\nApproximate Area = 636 sq ft / 59.1 sq m (includes store)\nFor identification only - Not to scale\nGarden\naan\n| <ths\na\n| ; V\n\u2014 | Store:\nfA\nSout\nKitchen /\nReception Room\n7 [-\u2014\u2014\nBedroom\nBedroom\n|\n\u2014\nGROUND FLOOR\n= if Floor plan produced in accordance with RICS Property Measurement Standards incorporating\nKe) Broaeny Intemational Property Measurement Standards (IPMS2 Residential). \u00a9 nichecom 2022. @ee\nLa] Measurer Produced for Barnard Marcus. REF: 802093 barnard marcus\n",
    "image": "./extracted_images/60561452.jpg",
    "link": "https://www.zoopla.co.uk//for-sale/details/60561452/",
    "listing_no": "60561452",
    "gmap": {
        "@type": "GeoCoordinates",
        "latitude": 51.442019,
        "longitude": -0.192303
    },
    "first_published": "2022-01-19T12:14:19",
    "last_sale_date": "2011-09-23",
    "last_sale_new": false,
    "deets": {
        "__typename": "ListingData",
        "listingId": "60561452",
        "publishedOn": "2022-01-19T12:14:19",
        "section": "for-sale",
        "additionalLinks": [
            {
                "__typename": "Media",
                "caption": "PDF Property Particulars",
                "original": "https://lc.zoocdn.com/18ff48e6ea3933b96b15569fab9b938b28296009.pdf",
                "type": "brochure",
                "url": null
            },
            {
                "__typename": "Media",
                "caption": "Full Details",
                "original": "https://www.barnardmarcus.co.uk/property/EAR104029",
                "type": "brochure",
                "url": null
            }
        ],
        "adTargeting": {
            "__typename": "ListingAnalyticsTaxonomy",
            "acorn": 15,
            "acornType": 15,
            "areaName": "London",
            "bedsMax": 2,
            "bedsMin": 2,
            "branchId": 17628,
            "branchLogoUrl": "https://st.zoocdn.com/zoopla_static_agent_logo_(592283).png",
            "branchName": "Barnard Marcus - Earlsfield",
            "brandName": "Barnard Marcus",
            "chainFree": true,
            "companyId": 14204,
            "countryCode": "gb",
            "countyAreaName": "London",
            "currencyCode": "GBP",
            "displayAddress": "Penwith Road, London SW18",
            "furnishedState": "",
            "groupId": 1,
            "hasEpc": true,
            "hasFloorplan": true,
            "incode": "4PY",
            "isRetirementHome": false,
            "isSharedOwnership": false,
            "listingCondition": "pre-owned",
            "listingId": 60561452,
            "listingsCategory": "residential",
            "listingStatus": "for_sale",
            "location": "London",
            "memberType": "agent",
            "numBaths": 1,
            "numBeds": 2,
            "numImages": 12,
            "numRecepts": 1,
            "outcode": "SW18",
            "postalArea": "SW",
            "postTownName": "London",
            "priceActual": 550000,
            "price": 550000,
            "priceMax": 550000,
            "priceMin": 550000,
            "priceQualifier": "",
            "propertyHighlight": "Garden",
            "propertyType": "flat",
            "regionName": "London",
            "section": "for-sale",
            "sizeSqFeet": "",
            "tenure": "leasehold",
            "zindex": 521642
        },
        "branch": {
            "__typename": "AgentBranch",
            "branchDetailsUri": "/find-agents/branch/barnard-marcus-earlsfield-earlsfield-17628/",
            "branchId": "17628",
            "branchResultsUri": "/for-sale/branch/barnard-marcus-earlsfield-earlsfield-17628/",
            "logoUrl": "https://st.zoocdn.com/zoopla_static_agent_logo_(592283).png",
            "phone": "020 8166 7289",
            "name": "Barnard Marcus - Earlsfield",
            "memberType": "agent",
            "address": "525 Garratt Lane, Earlsfield",
            "postcode": "SW18 4SR"
        },
        "pointsOfInterest": [
            {
                "__typename": "PointOfInterest",
                "title": "Earlsfield",
                "type": "national_rail_station",
                "distanceMiles": 0.2
            },
            {
                "__typename": "PointOfInterest",
                "title": "Earlsfield Primary School",
                "type": "uk_school_primary",
                "distanceMiles": 0.3
            },
            {
                "__typename": "PointOfInterest",
                "title": "Wimbledon Park Primary School",
                "type": "uk_school_primary",
                "distanceMiles": 0.3
            },
            {
                "__typename": "PointOfInterest",
                "title": "Wimbledon Park",
                "type": "london_underground_station",
                "distanceMiles": 0.6
            }
        ],
        "embeddedContent": {
            "__typename": "EmbeddedContent",
            "videos": null,
            "tours": [
                {
                    "__typename": "Media",
                    "url": "https://my.matterport.com/show?m=923uYW2xvvP"
                }
            ],
            "links": null,
            "smartViewings": null
        },
        "epc": {
            "__typename": "EPC",
            "image": [
                {
                    "__typename": "Media",
                    "caption": "EPC",
                    "filename": "1cebf41f964c24e4da4cf5401a3aaca4fd32544b.png",
                    "url": null
                }
            ],
            "pdf": null
        },
        "detailedDescription": "<strong>Summary</strong><br>A Victorian two bedroom ground floor maisonette with private garden, moments from Earlsfield station.<br><br><strong>Description</strong><br>A Victorian two bedroom ground floor maisonette with private garden, moments from Earlsfield station.<br><br>The property, which has a versatile layout, benefits from a wealth of character, with high ceilings and many original features. Further benefits include a private rear garden with an open aspect to the west.<br><br>Penwith Road is located in the heart of Earlsfield, within close proximity of its popular coffee shops, bars and restaurants.<br>Offered for sale with no upward chain.<br><br>We currently hold lease details as displayed above, should you require further information please contact the branch. Please note additional fees could be incurred for items such as leasehold packs.<br><br>1. Money laundering regulations: Intending purchasers will be asked to produce identification documentation at a later stage and we would ask for your co-operation in order that there will be no delay in agreeing the sale. <br>2. General: While we endeavour to make our sales particulars fair, accurate and reliable, they are only a general guide to the property and, accordingly, if there is any point which is of particular importance to you, please contact the office and we will be pleased to check the position for you, especially if you are contemplating travelling some distance to view the property. <br>3. The measurements indicated are supplied for guidance only and as such must be considered incorrect. <br>4. Services: Please note we have not tested the services or any of the equipment or appliances in this property, accordingly we strongly advise prospective buyers to commission their own survey or service reports before finalising their offer to purchase. <br>5. These particulars are issued in good faith but do not constitute representations of fact or form part of any offer or contract. The matters referred to in these particulars should be independently verified by prospective buyers or tenants. Neither sequence (UK) limited nor any of its employees or agents has any authority to make or give any representation or warranty whatever in relation to this property.",
        "features": {
            "__typename": "Features",
            "bullets": [
                "Victorian One/Two Bedroom Victorian Maisonette",
                "Versatile Layout",
                "Private Garden with an Open Aspect to the West",
                "Moments from Earlsfield Station",
                "No Upward Chain"
            ],
            "flags": {
                "__typename": "FeatureFlag",
                "furnishedState": null,
                "studentFriendly": false,
                "tenure": {
                    "__typename": "Label",
                    "name": "leasehold",
                    "label": "Leasehold"
                },
                "availableFromDate": null
            },
            "highlights": [
                {
                    "__typename": "FeatureHighlight",
                    "description": null,
                    "label": "Garden"
                }
            ]
        },
        "floorPlan": {
            "__typename": "FloorPlan",
            "image": [
                {
                    "__typename": "Media",
                    "filename": "8329d18b1a67db92de7b6c7354576634ff8cafde.jpg",
                    "caption": null
                }
            ],
            "links": null,
            "pdf": null
        },
        "propertyImage": [
            {
                "__typename": "Media",
                "filename": "a882c721e7bbd50a043f1e78a73b2c3af12cfa27.jpg",
                "caption": null
            },
            {
                "__typename": "Media",
                "filename": "7b99e91d19dc1d9e8ab560d600b3c2c51af75300.jpg",
                "caption": null
            },
            {
                "__typename": "Media",
                "filename": "a2c8e3d01da1d403b9269b26cd9fa80eb60fe9e6.jpg",
                "caption": null
            },
            {
                "__typename": "Media",
                "filename": "bc7ba5f40f2b79306f1e130e37f8b4a9583e8f08.jpg",
                "caption": null
            },
            {
                "__typename": "Media",
                "filename": "8ebdef2bfdcf9d80368c51312d80c14a770f1a2c.jpg",
                "caption": null
            },
            {
                "__typename": "Media",
                "filename": "ec37bd9be037d02a4fe511c6a4d3a1e508e949be.jpg",
                "caption": null
            },
            {
                "__typename": "Media",
                "filename": "e7ef1b16b73e11e430507f45c00c3dd441ddacb7.jpg",
                "caption": null
            },
            {
                "__typename": "Media",
                "filename": "94b2494c9159ba942a0b8deb7b9424dab1d7fb91.jpg",
                "caption": null
            },
            {
                "__typename": "Media",
                "filename": "7551b7fbc576a50bb20f23158d0cd3295059b021.jpg",
                "caption": null
            },
            {
                "__typename": "Media",
                "filename": "a740fe9442723e5de09e6165f02eeff90e770d6d.jpg",
                "caption": null
            },
            {
                "__typename": "Media",
                "filename": "02829bfcd0035aacb232a01b7a744639a3391311.jpg",
                "caption": null
            },
            {
                "__typename": "Media",
                "filename": "bf436018bdd096e36ebd691bb0820da2d2cf96db.jpg",
                "caption": null
            }
        ],
        "analyticsTaxonomy": {
            "__typename": "ListingAnalyticsTaxonomy",
            "location": "London",
            "regionName": "London",
            "section": "for-sale",
            "acorn": 15,
            "acornType": 15,
            "areaName": "London",
            "bedsMax": 2,
            "bedsMin": 2,
            "branchId": 17628,
            "branchLogoUrl": "https://st.zoocdn.com/zoopla_static_agent_logo_(592283).png",
            "branchName": "Barnard Marcus - Earlsfield",
            "brandName": "Barnard Marcus",
            "chainFree": true,
            "companyId": 14204,
            "countryCode": "gb",
            "countyAreaName": "London",
            "currencyCode": "GBP",
            "displayAddress": "Penwith Road, London SW18",
            "furnishedState": "",
            "groupId": 1,
            "hasEpc": true,
            "hasFloorplan": true,
            "incode": "4PY",
            "isRetirementHome": false,
            "isSharedOwnership": false,
            "listingCondition": "pre-owned",
            "listingId": 60561452,
            "listingsCategory": "residential",
            "listingStatus": "for_sale",
            "memberType": "agent",
            "numBaths": 1,
            "numBeds": 2,
            "numImages": 12,
            "numRecepts": 1,
            "outcode": "SW18",
            "postalArea": "SW",
            "postTownName": "London",
            "priceActual": 550000,
            "price": 550000,
            "priceMax": 550000,
            "priceMin": 550000,
            "priceQualifier": "",
            "propertyHighlight": "Garden",
            "propertyType": "flat",
            "sizeSqFeet": "",
            "tenure": "leasehold",
            "zindex": 521642
        },
        "title": "2 bed flat for sale",
        "metaTitle": "2 bed flat for sale in Penwith Road, London SW18 - Zoopla",
        "metaDescription": "2 bed flat for sale in Penwith Road, London SW18, selling for \u00a3550,000 from Barnard Marcus - Earlsfield. See property details on Zoopla or browse all our range of properties in Penwith Road, London SW18.",
        "listingUris": {
            "__typename": "ListingUris",
            "detail": "/for-sale/details/60561452/"
        },
        "location": {
            "__typename": "ListingLocation",
            "coordinates": {
                "__typename": "LocationCoordinates",
                "latitude": 51.442019,
                "longitude": -0.192303
            }
        },
        "displayAddress": "Penwith Road, London SW18",
        "priceHistory": {
            "__typename": "PriceHistory",
            "firstPublished": {
                "__typename": "PriceHistoryFirstPublished",
                "firstPublishedDate": "2022-01-19T12:14:19",
                "priceLabel": "\u00a3550,000"
            },
            "lastSale": {
                "__typename": "PriceHistoryLastSale",
                "date": "2011-09-23",
                "newBuild": false,
                "price": 296000,
                "priceLabel": "\u00a3296,000",
                "recentlySold": false
            },
            "priceChanges": null
        },
        "viewCount": {
            "__typename": "ViewCount",
            "viewCount30day": 191
        },
        "administrationFees": null,
        "content": {
            "__typename": "MediaContent",
            "floorPlan": [
                {
                    "__typename": "Media",
                    "original": "https://lc.zoocdn.com/8329d18b1a67db92de7b6c7354576634ff8cafde.jpg"
                }
            ]
        },
        "statusSummary": null,
        "tags": [],
        "counts": {
            "__typename": "RoomCount",
            "numBedrooms": 2,
            "numBathrooms": 1,
            "numLivingRooms": 1
        },
        "floorArea": null,
        "pricing": {
            "__typename": "ListingPricing",
            "label": "\u00a3550,000",
            "priceQualifierLabel": null,
            "rentFrequencyLabel": null,
            "isAuction": false,
            "pricePerFloorAreaUnit": null,
            "alternateRentFrequencyPrice": null
        },
        "analyticsEcommerce": {
            "__typename": "ListingAnalyticsEcommerce",
            "brand": "Barnard Marcus",
            "category": "for-sale/resi/agent/pre-owned/gb",
            "id": 60561452,
            "name": "FS_Contact",
            "price": 1,
            "quantity": 1,
            "variant": "premium plus"
        },
        "uuid": "56B30DDC-94A2-11EC-8306-B4140E674736",
        "marketStats": {
            "__typename": "MarketStatsResults",
            "areaName": "SW18",
            "areaNameUri": "london/sw18/wandsworth-earlsfield",
            "propertyTypeGroup": "flat",
            "askingPrices": {
                "__typename": "AskingPrices",
                "toRent": {
                    "__typename": "AskingPrice",
                    "meanValue": 2440.1807909604536
                }
            },
            "historicalEstimates": [
                {
                    "__typename": "HistoricalEstimate",
                    "overMonth": "0",
                    "value": 545740,
                    "pctChangeSince": 0,
                    "date": "2022-02-26",
                    "changeSince": 0
                },
                {
                    "__typename": "HistoricalEstimate",
                    "overMonth": "3",
                    "value": 548436,
                    "pctChangeSince": -0.492,
                    "date": "2021-11-26",
                    "changeSince": -2696
                },
                {
                    "__typename": "HistoricalEstimate",
                    "overMonth": "6",
                    "value": 548784,
                    "pctChangeSince": -0.555,
                    "date": "2021-08-26",
                    "changeSince": -3044
                },
                {
                    "__typename": "HistoricalEstimate",
                    "overMonth": "12",
                    "value": 571676,
                    "pctChangeSince": -4.537,
                    "date": "2021-02-26",
                    "changeSince": -25936
                },
                {
                    "__typename": "HistoricalEstimate",
                    "overMonth": "60",
                    "value": 553935,
                    "pctChangeSince": -1.479,
                    "date": "2017-02-26",
                    "changeSince": -8195
                },
                {
                    "__typename": "HistoricalEstimate",
                    "overMonth": "120",
                    "value": 381867,
                    "pctChangeSince": 42.914,
                    "date": "2012-02-26",
                    "changeSince": 163873
                },
                {
                    "__typename": "HistoricalEstimate",
                    "overMonth": "180",
                    "value": 348838,
                    "pctChangeSince": 56.445,
                    "date": "2007-02-26",
                    "changeSince": 196902
                },
                {
                    "__typename": "HistoricalEstimate",
                    "overMonth": "240",
                    "value": 212532,
                    "pctChangeSince": 156.78,
                    "date": "2002-02-26",
                    "changeSince": 333208
                }
            ],
            "sales": [
                {
                    "__typename": "HistoricalSales",
                    "overYear": "1",
                    "mean": 554541,
                    "newBuilds": 19,
                    "numSales": 470
                },
                {
                    "__typename": "HistoricalSales",
                    "overYear": "3",
                    "mean": 543782,
                    "newBuilds": 55,
                    "numSales": 1296
                },
                {
                    "__typename": "HistoricalSales",
                    "overYear": "5",
                    "mean": 547279,
                    "newBuilds": 111,
                    "numSales": 2421
                },
                {
                    "__typename": "HistoricalSales",
                    "overYear": "7",
                    "mean": 550771,
                    "newBuilds": 488,
                    "numSales": 4197
                }
            ],
            "recentSales": [
                {
                    "__typename": "RecentSale",
                    "date": "2021-06-30T00:00:00Z",
                    "price": 551500,
                    "propertyId": 23384376,
                    "streetAddress": "93 Penwith Road",
                    "uri": "93-penwith-road/london/sw18-4py"
                },
                {
                    "__typename": "RecentSale",
                    "date": "2021-06-30T00:00:00Z",
                    "price": 595000,
                    "propertyId": 23384434,
                    "streetAddress": "159 Penwith Road",
                    "uri": "159-penwith-road/london/sw18-4pz"
                },
                {
                    "__typename": "RecentSale",
                    "date": "2021-06-10T00:00:00Z",
                    "price": 450000,
                    "propertyId": 23384536,
                    "streetAddress": "130 Penwith Road",
                    "uri": "130-penwith-road/london/sw18-4qe"
                },
                {
                    "__typename": "RecentSale",
                    "date": "2021-04-21T00:00:00Z",
                    "price": 613750,
                    "propertyId": 23384544,
                    "streetAddress": "130a Penwith Road",
                    "uri": "130a-penwith-road/london/sw18-4qe"
                },
                {
                    "__typename": "RecentSale",
                    "date": "2021-04-01T00:00:00Z",
                    "price": 624000,
                    "propertyId": 23384335,
                    "streetAddress": "37a Penwith Road",
                    "uri": "37a-penwith-road/london/sw18-4pu"
                },
                {
                    "__typename": "RecentSale",
                    "date": "2021-12-20T00:00:00Z",
                    "price": 510000,
                    "propertyId": 23379218,
                    "streetAddress": "13 Heathfield Square",
                    "uri": "13-heathfield-square/london/sw18-3hy"
                },
                {
                    "__typename": "RecentSale",
                    "date": "2021-12-17T00:00:00Z",
                    "price": 860000,
                    "propertyId": 23377537,
                    "streetAddress": "6 Wells Place",
                    "uri": "6-wells-place/london/sw18-3bf"
                },
                {
                    "__typename": "RecentSale",
                    "date": "2021-12-14T00:00:00Z",
                    "price": 696000,
                    "propertyId": 23384628,
                    "streetAddress": "16a Duntshill Road",
                    "uri": "16a-duntshill-road/london/sw18-4ql"
                },
                {
                    "__typename": "RecentSale",
                    "date": "2021-12-13T00:00:00Z",
                    "price": 1325500,
                    "propertyId": 23388776,
                    "streetAddress": "94 Elsenham Street",
                    "uri": "94-elsenham-street/london/sw18-5nt"
                },
                {
                    "__typename": "RecentSale",
                    "date": "2021-12-13T00:00:00Z",
                    "price": 511000,
                    "propertyId": 23383425,
                    "streetAddress": "31 Steerforth Street",
                    "uri": "31-steerforth-street/london/sw18-4hf"
                }
            ]
        }
    }
}